LICENSE
MANIFEST.in
README.md
setup.cfg
setup.py
docassemble/__init__.py
docassemble.EJCRC.egg-info/PKG-INFO
docassemble.EJCRC.egg-info/SOURCES.txt
docassemble.EJCRC.egg-info/dependency_links.txt
docassemble.EJCRC.egg-info/namespace_packages.txt
docassemble.EJCRC.egg-info/not-zip-safe
docassemble.EJCRC.egg-info/top_level.txt
docassemble/EJCRC/__init__.py
docassemble/EJCRC/data/questions/LLT_Ejectment_Case_Start.yml
docassemble/EJCRC/data/questions/LLT_Ejectment_Case_Started.yml
docassemble/EJCRC/data/questions/LLT_Redirect.yml
docassemble/EJCRC/data/questions/LLT_complaint.yml
docassemble/EJCRC/data/questions/LLT_landing_screen.yml
docassemble/EJCRC/data/questions/LLT_or_ejectment_defendant.yml
docassemble/EJCRC/data/questions/LLT_or_ejectment_plaintiff.yml
docassemble/EJCRC/data/questions/alternate_service.yml
docassemble/EJCRC/data/questions/answer_to_LLT.yml
docassemble/EJCRC/data/questions/answer_to_civil_complaint.yml
docassemble/EJCRC/data/questions/appeal_LLT_case.yml
docassemble/EJCRC/data/questions/appeal_LLT_muni_plaintiff.yml
docassemble/EJCRC/data/questions/appeal_muni_LLT_case.yml
docassemble/EJCRC/data/questions/case_id_help.yml
docassemble/EJCRC/data/questions/case_unknown.yml
docassemble/EJCRC/data/questions/case_unknown1.yml
docassemble/EJCRC/data/questions/case_unknown2.yml
docassemble/EJCRC/data/questions/civil_complaint.yml
docassemble/EJCRC/data/questions/civil_complaint_entry.yml
docassemble/EJCRC/data/questions/court_common_pleas.yml
docassemble/EJCRC/data/questions/court_common_pleas1.yml
docassemble/EJCRC/data/questions/court_unknown.yml
docassemble/EJCRC/data/questions/court_unknown1.yml
docassemble/EJCRC/data/questions/default_judgment_praecipe.yml
docassemble/EJCRC/data/questions/ejectment_defendant.yml
docassemble/EJCRC/data/questions/ejectment_defendant_screen.yml
docassemble/EJCRC/data/questions/ejectment_plaintiff.yml
docassemble/EJCRC/data/questions/ejectment_plaintiff_screen.yml
docassemble/EJCRC/data/questions/interview_start.yml
docassemble/EJCRC/data/questions/mortgage.yml
docassemble/EJCRC/data/questions/municipal_court.yml
docassemble/EJCRC/data/questions/non_section_8.yml
docassemble/EJCRC/data/questions/petition_open.yml
docassemble/EJCRC/data/questions/petition_open1.yml
