Metadata-Version: 2.1
Name: docassemble.EJCRC
Version: 0.0.99
Summary: A docassemble extension.
Home-page: https://docassemble.org
Author: Evan Cernea
Author-email: evan.cernea@gmail.com
License: The MIT License (MIT)
Platform: UNKNOWN
